roar_py_carla/__init__.py
roar_py_carla/actors/__init__.py
roar_py_carla/actors/carla_actor.py
roar_py_carla/actors/carla_vehicle.py
roar_py_carla/base/__init__.py
roar_py_carla/base/carla_base.py
roar_py_carla/carla_agents/__init__.py
roar_py_carla/carla_agents/navigation/__init__.py
roar_py_carla/carla_agents/navigation/global_route_planner.py
roar_py_carla/carla_agents/tools/__init__.py
roar_py_carla/carla_agents/tools/misc.py
roar_py_carla/clients/__init__.py
roar_py_carla/clients/carla_instance.py
roar_py_carla/sensors/__init__.py
roar_py_carla/sensors/carla_accelerometer_sensor.py
roar_py_carla/sensors/carla_camera_sensor.py
roar_py_carla/sensors/carla_collision_sensor.py
roar_py_carla/sensors/carla_gnss_sensor.py
roar_py_carla/sensors/carla_gyroscope_sensor.py
roar_py_carla/sensors/carla_lidar_sensor.py
roar_py_carla/sensors/carla_location_in_world_sensor.py
roar_py_carla/sensors/carla_occupancy_map_sensor.py
roar_py_carla/sensors/carla_radar_sensor.py
roar_py_carla/sensors/carla_rotation_sensor.py
roar_py_carla/sensors/carla_velocimeter_sensor.py
roar_py_carla/utils/__init__.py
roar_py_carla/utils/convert_coordinate.py
roar_py_carla/worlds/__init__.py
roar_py_carla/worlds/carla_world.py
roar_py_carla-0.1.0.dist-info/LICENSE
roar_py_carla-0.1.0.dist-info/METADATA
roar_py_carla-0.1.0.dist-info/WHEEL
roar_py_carla-0.1.0.dist-info/top_level.txt
roar_py_carla-0.1.0.dist-info/RECORD
