Metadata-Version: 2.1
Name: roar-py-carla
Version: 0.1.0
Summary: ROAR_PY carla implementation
Home-page: https://github.com/augcog/ROAR_PY
Author: Yunhao Cao
License: MIT
Keywords: reinforcement learning,gymnasium,robotics,carla,carla-simulator
Classifier: Programming Language :: Python :: 3
Classifier: Intended Audience :: Education
Classifier: Intended Audience :: Science/Research
Classifier: License :: OSI Approved :: MIT License
Classifier: Operating System :: OS Independent
Classifier: Topic :: Scientific/Engineering :: Artificial Intelligence
Requires-Python: >=3.8
License-File: LICENSE
Requires-Dist: roar-py-core ==0.1.0
Requires-Dist: asyncio
Requires-Dist: numpy
Requires-Dist: carla >=0.9.12
Requires-Dist: networkx >=3.1
Requires-Dist: transforms3d >=0.4.1
